ape_tokens/__init__.py
ape_tokens/_cli.py
ape_tokens/config.py
ape_tokens/converters.py
ape_tokens/main.py
ape_tokens/managers.py
ape_tokens/py.typed
ape_tokens/testing.py
ape_tokens/types.py
ape_tokens/version.py
ape_tokens-0.8.8.dist-info/licenses/LICENSE
ape_tokens-0.8.8.dist-info/METADATA
ape_tokens-0.8.8.dist-info/WHEEL
ape_tokens-0.8.8.dist-info/entry_points.txt
ape_tokens-0.8.8.dist-info/top_level.txt
ape_tokens-0.8.8.dist-info/RECORD
