Metadata-Version: 2.4
Name: ape-tokens
Version: 0.8.8
Summary: ape-tokens: tokenlists plugin for Ape
Author-email: "ApeWorX Ltd." <admin@apeworx.io>
License-Expression: Apache-2.0
Project-URL: Homepage, https://github.com/ApeWorX/ape-tokens
Project-URL: Repository, https://github.com/ApeWorX/ape-tokens
Keywords: ethereum
Classifier: Development Status :: 5 - Production/Stable
Classifier: Intended Audience :: Developers
Classifier: Natural Language :: English
Classifier: Operating System :: MacOS
Classifier: Operating System :: POSIX
Classifier: Programming Language :: Python :: 3
Classifier: Programming Language :: Python :: 3.10
Classifier: Programming Language :: Python :: 3.11
Classifier: Programming Language :: Python :: 3.12
Classifier: Programming Language :: Python :: 3.13
Classifier: Programming Language :: Python :: 3.14
Requires-Python: <4,>=3.10
License-File: LICENSE
Requires-Dist: eth-ape<0.9,>=0.8.1
Requires-Dist: tokenlists>=0.1.7
Dynamic: license-file
